{
  "version": "2026-06-20",
  "ssot": "docs/notes/TOOL_NAMING_AGENT_PLAYBOOK.md · docs/DESIGN_GUIDELINE.md §1.3",
  "namingLegend": {
    "id": "コード識別子（ファイル名 · data-sg-tool-id · JS）",
    "conceptName": "概念名（本文 · 帳票種別 · 説明）",
    "productName": "プロダクト名（白ヘッダー data-sg-title · Product ページ）",
    "navLabel": "ナビ短ラベル（SUGUDASU 接頭辞なし）",
    "name": "開発バッジ用の長い表示名（レジストリ互換）",
    "hubCardTitle": "Hub カード h3 = conceptName（SUGUDASU 接頭辞なし）"
  },
  "stageLegend": {
    "alpha": "骨格確認中。欠落・不具合があり得ます。",
    "beta": "主要機能は動作。品質担保・仕様変更が残ります。",
    "gamma": "リリース候補。細部調整・収益導線が残る場合あり。",
    "stable": "安定運用。大きな仕様変更は changelog で告知。"
  },
  "tools": {
    "hub": {
      "file": "hub.html",
      "conceptName": "ツール一覧",
      "productName": "ツール一覧",
      "navLabel": "一覧",
      "navIcon": "🏠",
      "inNav": true,
      "navOrder": 1,
      "name": "ツール一覧",
      "version": "1.1.0",
      "stage": "gamma",
      "statusNote": "ツール入口 · SEO・回遊導線を継続改善（Backlog §2-5）"
    },
    "invoice": {
      "file": "invoice.html",
      "conceptName": "請求書",
      "productName": "SUGUDASU 請求書",
      "navLabel": "請求書",
      "navIcon": "📄",
      "inNav": true,
      "navOrder": 2,
      "name": "見積・納品・請求書",
      "version": "1.3.0",
      "stage": "beta",
      "statusNote": "源泉10.21% · 内税8/10%分離 · A4マルチ+下書き",
      "categoryId": "docs"
    },
    "stamp": {
      "file": "stamp.html",
      "conceptName": "印鑑・認印",
      "productName": "SUGUDASU 電子印鑑",
      "navLabel": "印鑑",
      "navIcon": "🔴",
      "inNav": true,
      "navOrder": 3,
      "name": "電子印鑑（請求書用）",
      "version": "1.0.0",
      "stage": "beta",
      "statusNote": "認印のみ · 明朝/行書風 · 請求書 handoff · 角印はアップロード",
      "categoryId": "docs"
    },
    "receipt": {
      "file": "receipt.html",
      "conceptName": "領収書",
      "productName": "SUGUDASU 領収書",
      "navLabel": "領収書",
      "navIcon": "🧾",
      "inNav": true,
      "navOrder": 4,
      "name": "手取り逆引き・領収書",
      "version": "1.1.0",
      "stage": "gamma",
      "statusNote": "MVP+A4マルチ+URL共有済 · 内税等は後続（§9）",
      "categoryId": "docs"
    },
    "label": {
      "file": "label.html",
      "conceptName": "宛名ラベル",
      "productName": "SUGUDASU ラベル",
      "navLabel": "ラベル",
      "navIcon": "🏷️",
      "inNav": true,
      "navOrder": 5,
      "name": "宛名ラベル",
      "version": "1.1.0",
      "stage": "gamma",
      "statusNote": "一括貼付: ヘッダー行除外 · 姓名スペース保護 · sg-segment統一済",
      "categoryId": "docs"
    },
    "shift": {
      "file": "shift.html",
      "conceptName": "シフト表",
      "productName": "SUGUDASU シフト",
      "navLabel": "シフト",
      "navIcon": "📅",
      "inNav": true,
      "navOrder": 6,
      "name": "シフト表",
      "version": "1.1.0",
      "stage": "beta",
      "statusNote": "P1: 公平性・改ページ・FIXロックの品質担保（§4-1 · §6）",
      "categoryId": "staffing"
    },
    "report": {
      "file": "report.html",
      "conceptName": "議事録整形",
      "productName": "SUGUDASU 議事録",
      "navLabel": "議事録",
      "navIcon": "📝",
      "inNav": true,
      "navOrder": 7,
      "name": "議事録・報告書",
      "version": "1.0.0",
      "stage": "gamma",
      "statusNote": "UX改善済 · チャット共有Phase2は未（§2-4）",
      "categoryId": "text"
    },
    "reverse": {
      "file": "reverse.html",
      "conceptName": "逆引き辞典",
      "productName": "SUGUDASU 逆引き",
      "navLabel": "逆引き",
      "navIcon": "📖",
      "inNav": true,
      "navOrder": 8,
      "name": "逆引き辞典",
      "version": "1.0.0",
      "stage": "gamma",
      "statusNote": "STEP5 UX改善完了 · sns相互導線はP2（§1-2 · §4-3b）",
      "categoryId": "text"
    },
    "normalize": {
      "file": "normalize.html",
      "conceptName": "テキスト整え",
      "productName": "SUGUDASU 全角半角整え",
      "navLabel": "全角半角",
      "navIcon": "🔤",
      "inNav": true,
      "navOrder": 9,
      "name": "全角半角・テキスト整え",
      "version": "1.4.0",
      "stage": "beta",
      "statusNote": "500行cap · 行整理 · 伏字3種 · 日付統一 · sql_in/tab_to_comma · T03",
      "categoryId": "text"
    },
    "search-query": {
      "file": "search-query.html",
      "conceptName": "Google検索式",
      "productName": "SUGUDASU 検索式ビルダー",
      "navLabel": "検索式",
      "navIcon": "🔍",
      "inNav": true,
      "navOrder": 9.2,
      "name": "検索式ビルダー（filetype / site）",
      "version": "0.1.0",
      "stage": "alpha",
      "statusNote": "Google検索式のローカル組み立て · 非送信 · SEARCH_QUERY_BUILDER_SPEC.md",
      "categoryId": "text"
    },
    "table-conv": {
      "file": "table-conv.html",
      "conceptName": "表データ変換",
      "productName": "SUGUDASU 表変換",
      "navLabel": "表変換",
      "navIcon": "📊",
      "inNav": true,
      "navOrder": 9.5,
      "name": "表データ相互コンバータ",
      "version": "1.0.0",
      "stage": "beta",
      "statusNote": "Excel貼付/CSV→MD·JSON·TSV · Shift-JIS · 非送信 · 5,000行",
      "categoryId": "text"
    },
    "webp-to-jpg": {
      "file": "webp-to-jpg.html",
      "conceptName": "WebP変換",
      "productName": "SUGUDASU WebP変換",
      "navLabel": "WebP→JPG",
      "navIcon": "🖼️",
      "inNav": true,
      "navOrder": 10,
      "name": "WebP→JPG/PNG",
      "version": "1.0.0",
      "stage": "beta",
      "statusNote": "WebP→JPG/PNG · 非送信（アップロード型と差別化）· T09",
      "categoryId": "media"
    },
    "video-frame": {
      "file": "video-frame.html",
      "conceptName": "動画コマ抜き",
      "productName": "SUGUDASU 動画コマ抜き",
      "navLabel": "動画コマ抜き",
      "navIcon": "🎬",
      "inNav": true,
      "navOrder": 10.2,
      "name": "動画から静止画PNG（コマ抜き）",
      "version": "0.1.0",
      "stage": "alpha",
      "statusNote": "ローカル MP4/WebM → PNG · 非送信 · VIDEO_FRAME_PNG_SPEC.md",
      "categoryId": "media"
    },
    "mask": {
      "file": "mask.html",
      "conceptName": "画像マスク",
      "productName": "SUGUDASU マスク",
      "navLabel": "マスク",
      "navIcon": "🛡️",
      "inNav": true,
      "navOrder": 10.5,
      "name": "スクショ機密消し",
      "version": "0.1.0",
      "stage": "alpha",
      "statusNote": "ぼかし/黒塗り/同色塗り/スタンプ/注釈（矢印·枠） · Canvas非送信 · マニュアル向け · T09b",
      "categoryId": "media"
    },
    "image-trim": {
      "file": "image-trim.html",
      "conceptName": "画像切り出し",
      "productName": "SUGUDASU 画像切り出し",
      "navLabel": "画像切り出し",
      "navIcon": "✂️",
      "inNav": true,
      "navOrder": 10.6,
      "name": "指定サイズ画像切出し",
      "version": "0.1.1",
      "stage": "alpha",
      "statusNote": "枠固定 · cover-fit · SNS/資料プリセット · 非送信 · Ctrl+V",
      "categoryId": "media"
    },
    "clipboard-trim": {
      "file": "clipboard-trim.html",
      "conceptName": "余白トリム",
      "productName": "SUGUDASU 余白トリム",
      "navLabel": "余白トリム",
      "navIcon": "📐",
      "inNav": true,
      "navOrder": 10.65,
      "name": "クリップボード余白自動除去",
      "version": "0.1.0",
      "stage": "alpha",
      "statusNote": "Ctrl+V → 余白自動除去 → PNGコピー · 非送信 · CLIPBOARD_TRIM_SPEC.md",
      "categoryId": "media"
    },
    "watermark": {
      "file": "watermark.html",
      "conceptName": "画像透かし",
      "productName": "SUGUDASU 透かし",
      "navLabel": "透かし",
      "navIcon": "💧",
      "inNav": true,
      "navOrder": 10.7,
      "name": "画像透かし一括",
      "version": "0.1.0",
      "stage": "alpha",
      "statusNote": "文字/ロゴ · 9点 · 透過3段階 · ZIP · 非送信 · WATERMARK_TOOL_SPEC.md",
      "categoryId": "media"
    },
    "pdf-images": {
      "file": "pdf-images.html",
      "conceptName": "PDF画像抽出",
      "productName": "SUGUDASU PDF画像抽出",
      "navLabel": "PDF画像",
      "navIcon": "📄",
      "inNav": true,
      "navOrder": 10.75,
      "name": "PDF埋め込み画像抽出",
      "version": "0.1.0",
      "stage": "alpha",
      "statusNote": "埋め込み画像のみ · ZIP · pdfjs 5.4.296 · PDF_IMAGE_EXTRACT_SPEC.md",
      "categoryId": "media"
    },
    "test-data": {
      "file": "test-data.html",
      "conceptName": "テストデータ",
      "productName": "SUGUDASU テストデータ",
      "navLabel": "テストデータ",
      "navIcon": "🧪",
      "inNav": true,
      "navOrder": 10.8,
      "name": "テスト用ダミーデータ生成",
      "version": "0.5.0",
      "stage": "alpha",
      "statusNote": "社員マスタ25万一括CSV · IDオフセット · 日付統一 · T10",
      "categoryId": "devtest"
    },
    "group-split": {
      "file": "group-split.html",
      "conceptName": "班分け",
      "productName": "SUGUDASU 班分け",
      "navLabel": "班分け",
      "navIcon": "👥",
      "inNav": true,
      "navOrder": 11,
      "name": "グループ分け",
      "version": "1.2.4",
      "stage": "beta",
      "statusNote": "PC→スマホ同期メモ · 緩和モード · M02 タップ再編 · セッションJSON · Phase C · 250名cap · T11",
      "categoryId": "people"
    },
    "match-board": {
      "file": "match-board.html",
      "conceptName": "ドラフト会議",
      "productName": "SUGUDASU ドラフト会議",
      "navLabel": "ドラフト",
      "navIcon": "🧩",
      "inNav": true,
      "navOrder": 11.25,
      "name": "希望順位割当ボード",
      "version": "0.1.0",
      "stage": "alpha",
      "statusNote": "第1〜3希望×定員の長時間調整 · Undo/Redo · JSON再開 · 非送信",
      "categoryId": "people"
    },
    "slot-board": {
      "file": "slot-board.html",
      "conceptName": "枠取りパレット",
      "productName": "SUGUDASU 枠取りパレット",
      "navLabel": "枠取り",
      "navIcon": "📦",
      "inNav": true,
      "navOrder": 11.3,
      "name": "定員付き枠取りカンバン",
      "version": "0.1.0",
      "stage": "alpha",
      "statusNote": "制限付きカンバン · 超過赤表示 · 復元コード · TSV · 非送信",
      "categoryId": "people"
    },
    "planning-poker": {
      "file": "planning-poker.html",
      "conceptName": "見積会議",
      "productName": "SUGUDASU 見積会議",
      "navLabel": "見積会議",
      "navIcon": "🃏",
      "inNav": true,
      "navOrder": 11.35,
      "name": "見積会議（Planning Poker）",
      "version": "0.1.0",
      "stage": "alpha",
      "statusNote": "司会代行で全員分伏せ入力 · 同時Reveal · 最大/最小理由 · CSV · 非送信（多人端末同期は検討中）",
      "categoryId": "people"
    },
    "timeline": {
      "file": "timeline.html",
      "conceptName": "イベント進行",
      "productName": "SUGUDASU イベント進行",
      "navLabel": "進行",
      "navIcon": "⏱️",
      "inNav": true,
      "navOrder": 11.5,
      "name": "イベント進行タイムライン",
      "version": "0.1.0",
      "stage": "alpha",
      "statusNote": "T13 M01 · 連動再計算 · ±5 · 差し込み · TSVコピー · 非送信 · alpha",
      "categoryId": "ops"
    },
    "present": {
      "file": "present.html",
      "conceptName": "ギフト",
      "productName": "SUGUDASU ギフト",
      "navLabel": "ギフト",
      "navIcon": "🎁",
      "inNav": true,
      "navOrder": 12,
      "name": "ギフトサジェスター",
      "version": "1.0.0",
      "stage": "gamma",
      "statusNote": "Amazon主戦場 · アフィ最適化はP1（§2-1 · §2-3）",
      "categoryId": "ops"
    },
    "fair-draw": {
      "file": "fair-draw.html",
      "conceptName": "公平抽選",
      "productName": "SUGUDASU 抽選",
      "navLabel": "抽選",
      "navIcon": "🎲",
      "inNav": true,
      "navOrder": 13,
      "name": "公平抽選・景品チェック（証跡PDF）",
      "version": "1.6.0",
      "stage": "beta",
      "statusNote": "Connpass CSV取込 · 証跡3点セット · 名簿スナップショット",
      "categoryId": "people"
    },
    "warikan": {
      "file": "warikan.html",
      "conceptName": "割り勘",
      "productName": "SUGUDASU 割り勘",
      "navLabel": "割り勘",
      "navIcon": "💰",
      "inNav": true,
      "navOrder": 14,
      "name": "傾斜割り勘",
      "version": "1.1.0",
      "stage": "gamma",
      "statusNote": "端数過不足ヒーロー表示 · sg-copy-feedback · Xシェア導線済",
      "categoryId": "ops"
    },
    "budget-trim": {
      "file": "budget-trim.html",
      "conceptName": "引き算パレット",
      "productName": "SUGUDASU 引き算パレット",
      "navLabel": "予算引き算",
      "navIcon": "✂️",
      "inNav": true,
      "navOrder": 13.9,
      "name": "予算引き算パレット",
      "version": "0.1.0",
      "stage": "alpha",
      "statusNote": "合計/上限の超過表示 · ±1万/10万キー · ハッシュ共有 · TSV · グラフなし · BUDGET_TRIM_SPEC.md",
      "categoryId": "ops"
    },
    "sns": {
      "file": "sns.html",
      "conceptName": "SNSデコ文字",
      "productName": "SUGUDASU SNS",
      "navLabel": "SNS",
      "navIcon": "✨",
      "inNav": true,
      "navOrder": 15,
      "name": "SNSデコ文字",
      "version": "1.1.0",
      "stage": "gamma",
      "statusNote": "font-converter 分離 · プレビュー/お手本は /sns · 23フォントは /font-converter",
      "categoryId": "creative"
    },
    "link-qr": {
      "file": "link-qr.html",
      "conceptName": "リンク集QR",
      "productName": "SUGUDASU リンク集QR",
      "navLabel": "リンクQR",
      "navIcon": "📇",
      "inNav": true,
      "navOrder": 16,
      "name": "リンク集QR（即席プロフィール）",
      "version": "0.1.0",
      "stage": "alpha",
      "statusNote": "URL #fragment エンコード · 非送信 · イベント懇親会フォロー交換（LINK_QR_TOOL_SPEC.md）",
      "categoryId": "ops"
    },
    "qr-reader": {
      "file": "qr-reader.html",
      "conceptName": "QR読取",
      "productName": "SUGUDASU QR読取",
      "navLabel": "QR読取",
      "navIcon": "📷",
      "inNav": true,
      "navOrder": 16.5,
      "name": "QR読取（カメラ・貼り付け・画面共有）",
      "version": "0.1.0",
      "stage": "alpha",
      "statusNote": "カメラ/ファイル/貼り付け/画面共有 · 非送信 · link-qr形式カード表示",
      "categoryId": "ops"
    },
    "diff": {
      "file": "diff.html",
      "conceptName": "差分チェック",
      "productName": "SUGUDASU 差分チェック",
      "navLabel": "差分",
      "navIcon": "🔎",
      "inNav": true,
      "navOrder": 16.7,
      "name": "差分チェック",
      "version": "0.1.0",
      "stage": "alpha",
      "statusNote": "危険な変更の優先表示 · 非送信 · 保存なし · コピー/印刷",
      "categoryId": "text"
    },
    "time-calc": {
      "file": "time-calc.html",
      "conceptName": "時給計算",
      "productName": "SUGUDASU 時給計算",
      "navLabel": "時給計算",
      "navIcon": "⏳",
      "inNav": true,
      "navOrder": 16.8,
      "name": "時給計算（勤務時間合計 + 時給換算）",
      "version": "0.2.0",
      "stage": "alpha",
      "statusNote": "テンキー正規（コロン不要）· 候補↺ · 10進小数 · 時給換算 · 給与計算ではない",
      "categoryId": "staffing"
    },
    "font-converter": {
      "file": "font-converter.html",
      "conceptName": "フォント変換",
      "productName": "SUGUDASU フォント変換",
      "navLabel": null,
      "inNav": false,
      "name": "フォント変換",
      "version": "1.0.0",
      "stage": "gamma",
      "statusNote": "23フォントスタイル + 記号444 · /sns と相互リンク"
    },
    "updates": {
      "file": "updates.html",
      "conceptName": "更新履歴",
      "productName": "更新履歴",
      "navLabel": null,
      "inNav": false,
      "name": "更新履歴",
      "version": "1.0.0",
      "stage": "gamma",
      "statusNote": "changelog.json SSOT · 開発透明性の発信（§11 · §2-5）"
    },
    "roadmap": {
      "file": "roadmap.html",
      "conceptName": "開発ロードマップ",
      "productName": "開発ロードマップ",
      "navLabel": null,
      "inNav": false,
      "name": "開発ロードマップ",
      "version": "1.0.0",
      "stage": "gamma",
      "statusNote": "data/roadmap.json SSOT · 予定/検討中/対象外 · FEEDBACK_TRIAGE §6"
    },
    "statements": {
      "file": "statements.html",
      "conceptName": "約束",
      "productName": "SUGUDASU の約束",
      "navLabel": null,
      "inNav": false,
      "name": "SUGUDASU の約束",
      "version": "1.0.0",
      "stage": "gamma",
      "devBadge": false,
      "statusNote": "設計原則 · 非契約"
    },
    "privacy": {
      "file": "privacy.html",
      "conceptName": "プライバシーポリシー",
      "productName": "プライバシーポリシー",
      "navLabel": null,
      "inNav": false,
      "name": "プライバシーポリシー",
      "version": "1.0.0",
      "stage": "stable",
      "devBadge": false,
      "statusNote": "法務固定ページ"
    },
    "terms": {
      "file": "terms.html",
      "conceptName": "利用規約",
      "productName": "利用規約",
      "navLabel": null,
      "inNav": false,
      "name": "利用規約",
      "version": "1.0.0",
      "stage": "stable",
      "devBadge": false,
      "statusNote": "法務固定ページ"
    },
    "disclaimer": {
      "file": "disclaimer.html",
      "conceptName": "免責事項",
      "productName": "免責事項",
      "navLabel": null,
      "inNav": false,
      "name": "免責事項",
      "version": "1.0.0",
      "stage": "stable",
      "devBadge": false,
      "statusNote": "法務固定ページ"
    },
    "not-a-car": {
      "file": "not-a-car.html",
      "conceptName": "車ではなく書類",
      "productName": "車ではなく書類",
      "navLabel": null,
      "inNav": false,
      "name": "車ではなく書類",
      "version": "1.0.0",
      "stage": "stable",
      "devBadge": false,
      "statusNote": "SUBARU SUGDAS との混同防止"
    },
    "brand-logo-preview": {
      "file": "brand-logo-preview.html",
      "conceptName": "ロゴプレビュー",
      "productName": "ロゴタイプ比較",
      "navLabel": null,
      "inNav": false,
      "name": "ロゴプレビュー",
      "version": "0.1.0",
      "stage": "alpha",
      "statusNote": "内部プレビュー · sitemap対象外"
    }
  }
}
